cleaner/__init__.py
cleaner/cleaner.py
cleaner/main.py
pycleancodecli/__init__.py
pycleancodecli/cleaner.py
pycleancodecli/main.py
tests/__init__.py
tests/test_cleaner.py
pycleancodecli-0.2.dist-info/LICENSE
pycleancodecli-0.2.dist-info/METADATA
pycleancodecli-0.2.dist-info/WHEEL
pycleancodecli-0.2.dist-info/entry_points.txt
pycleancodecli-0.2.dist-info/top_level.txt
pycleancodecli-0.2.dist-info/RECORD
